[{"uri1":"http://purl.obolibrary.org/obo/pco.owl","uri2":"http://www.w3.org/1999/02/22-rdf-syntax-ns#","uri3":"http://www.w3.org/2002/07/owl#","number":73},{"uri1":"http://purl.obolibrary.org/obo/pco.owl","uri2":"http://www.w3.org/2000/01/rdf-schema#","uri3":"http://purl.obolibrary.org/obo/pco.owl","number":58},{"uri1":"http://purl.obolibrary.org/obo/pco.owl","uri2":"http://purl.obolibrary.org/obo/iao.owl","uri3":"http://purl.obolibrary.org/obo/iao.owl","number":44},{"uri1":"http://purl.obolibrary.org/obo/pco.owl","uri2":"http://purl.obolibrary.org/obo/iao.owl","uri3":"https://orcid.org/","number":22},{"uri1":"http://purl.obolibrary.org/obo/pco.owl","uri2":"http://www.w3.org/2000/01/rdf-schema#","uri3":"http://purl.obolibrary.org/obo/pato.owl","number":7},{"uri1":"http://purl.obolibrary.org/obo/pco.owl","uri2":"http://www.w3.org/2000/01/rdf-schema#","uri3":"http://www.geneontology.org/formats/oboInOwl#","number":7},{"uri1":"http://purl.obolibrary.org/obo/pco.owl","uri2":"http://www.w3.org/2000/01/rdf-schema#","uri3":"http://purl.obolibrary.org/obo/bfo.owl","number":4},{"uri1":"http://purl.obolibrary.org/obo/pco.owl","uri2":"http://purl.obolibrary.org/obo/iao.owl","uri3":"https://en.wikipedia.org/wiki/","number":4},{"uri1":"http://purl.obolibrary.org/obo/pco.owl","uri2":"http://purl.obolibrary.org/obo/iao.owl","uri3":"http://www.tiem.utk.edu/~gross/bioed/bealsmodules/","number":3},{"uri1":"http://purl.obolibrary.org/obo/pco.owl","uri2":"http://purl.obolibrary.org/obo/iao.owl","uri3":"https://en.wikipedia.org/wiki/Diversity_index#","number":3},{"uri1":"http://purl.obolibrary.org/obo/pco.owl","uri2":"http://www.w3.org/2000/01/rdf-schema#","uri3":"http://purl.obolibrary.org/obo/caro.owl","number":2},{"uri1":"http://purl.obolibrary.org/obo/pco.owl","uri2":"http://www.geneontology.org/formats/oboInOwl#","uri3":"http://edamontology.org/","number":1},{"uri1":"http://purl.obolibrary.org/obo/pco.owl","uri2":"http://www.w3.org/2000/01/rdf-schema#","uri3":"http://purl.obolibrary.org/obo/ecocore.owl","number":1},{"uri1":"http://purl.obolibrary.org/obo/pco.owl","uri2":"http://www.geneontology.org/formats/oboInOwl#","uri3":"http://purl.obolibrary.org/obo/geno.owl","number":1},{"uri1":"http://purl.obolibrary.org/obo/pco.owl","uri2":"http://www.w3.org/2000/01/rdf-schema#","uri3":"http://purl.obolibrary.org/obo/go.owl","number":1},{"uri1":"http://purl.obolibrary.org/obo/caro.owl","uri2":"http://www.w3.org/2000/01/rdf-schema#","uri3":"http://purl.obolibrary.org/obo/pco.owl","number":1},{"uri1":"http://purl.obolibrary.org/obo/pco.owl","uri2":"http://www.w3.org/2000/01/rdf-schema#","uri3":"http://purl.obolibrary.org/obo/stato.owl","number":1},{"uri1":"http://purl.obolibrary.org/obo/pco.owl","uri2":"http://www.geneontology.org/formats/oboInOwl#","uri3":"http://purl.obolibrary.org/obo/taxrank.owl","number":1},{"uri1":"http://purl.obolibrary.org/obo/pco.owl","uri2":"http://www.geneontology.org/formats/oboInOwl#","uri3":"http://rs.tdwg.org/ontology/voc/TaxonRank#","number":1},{"uri1":"http://purl.obolibrary.org/obo/pco.owl/","uri2":"http://www.w3.org/2000/01/rdf-schema#","uri3":"http://www.geneontology.org/formats/oboInOwl#","number":1},{"uri1":"http://purl.obolibrary.org/obo/pco.owl/","uri2":"http://www.w3.org/1999/02/22-rdf-syntax-ns#","uri3":"http://www.w3.org/2002/07/owl#","number":1},{"uri1":"http://purl.obolibrary.org/obo/pco.owl","uri2":"http://purl.obolibrary.org/obo/iao.owl","uri3":"https://www.ncbi.nlm.nih.gov/pmc/articles/PMC4811772/","number":1}]