[{"uri":"http://www.agroxml.de/rdf/vocabulary/general#","number":418},{"uri":"http://www.agroxml.de/rdf/vocabulary/machine#","number":282},{"uri":"http://www.agroxml.de/rdf/vocabulary/crop#","number":175},{"uri":"http://www.agroxml.de/rdf/vocabulary/operatingsupply#","number":126},{"uri":"http://www.agroxml.de/rdf/vocabulary/workprocess#","number":110},{"uri":"http://www.agroxml.de/rdf/vocabulary/workprocedure_ktbl#","number":105},{"uri":"http://www.agroxml.de/rdf/vocabulary/","number":57},{"uri":"http://www.agroxml.de/rdf/vocabulary/identifier#","number":41},{"uri":"http://www.agroxml.de/rdf/vocabulary/metadata#","number":10}]