[{"uri":"http://opendata.inra.fr/anaeeThes/","number":39309},{"uri":"http://www.w3.org/2004/02/skos/core#","number":21511},{"uri":"http://www.w3.org/1999/02/22-rdf-syntax-ns#","number":3745},{"uri":"http://purl.org/dc/terms/","number":3705},{"uri":"http://art.uniroma2.it/ontologies/vocbench#","number":3232},{"uri":"http://aims.fao.org/aos/agrovoc/","number":556},{"uri":"http://www.w3.org/ns/prov#","number":339},{"uri":"http://www.eionet.europa.eu/gemet/concept/","number":334},{"uri":"http://www.eionet.europa.eu/gemet/","number":315},{"uri":"http://www.anaee-France/thesaurus/","number":217},{"uri":"https://en.wikipedia.org/wiki/","number":5},{"uri":"http://aims.fao.org/aos/","number":4},{"uri":"http://ecoinformatics.org/oboe/oboe.1.0/","number":1},{"uri":"http://www.biomasse-territoire.info/fileadmin/site_bioter/documents_bioter/RMT_biomasse/","number":1},{"uri":"http://www.w3.org/2000/01/rdf-schema#","number":1}]