[{"uri":"http://www.w3.org/2002/07/owl#","number":157},{"uri":"http://www.w3id.org/def/irrig#","number":115},{"uri":"http://www.w3.org/ns/sosa/","number":45},{"uri":"http://www.w3id.org/def/caso#","number":42},{"uri":"http://www.w3.org/1999/02/22-rdf-syntax-ns#","number":22},{"uri":"https://w3id.org/def/saref4agri#","number":9},{"uri":"http://www.w3.org/ns/ssn/","number":4},{"uri":"https://w3id.org/saref#","number":4},{"uri":"http://www.w3.org/2001/XMLSchema#","number":3},{"uri":"https://orcid.org/","number":3},{"uri":"http://orcid.org/","number":1},{"uri":"http://purl.org/NET/rdflicense/","number":1},{"uri":"http://www.w3id.org/def/irrig/","number":1},{"uri":"https://www.irstea.fr/en/research/research-units/","number":1}]