[{"uri":"http://opendata.inra.fr/EOL/","number":4164},{"uri":"http://www.w3.org/2000/01/rdf-schema#","number":2081},{"uri":"http://purl.obolibrary.org/obo/iao.owl","number":1380},{"uri":"http://www.w3.org/1999/02/22-rdf-syntax-ns#","number":695},{"uri":"http://www.w3.org/2002/07/owl#","number":690},{"uri":"http://www.geneontology.org/formats/oboInOwl#","number":646},{"uri":"http://purl.org/dc/terms/","number":17},{"uri":"http://www.w3.org/2004/02/skos/core#","number":2},{"uri":"http://www.w3.org/ns/dcat#","number":2},{"uri":"http://prismstandard.org/namespaces/basic/2.0/","number":1},{"uri":"http://purl.org/dc/elements/1.1/","number":1},{"uri":"http://purl.org/pav/","number":1}]